Metadata-Version: 2.0
Name: signalr-client
Version: 0.0.7
Summary: Simple SignalR client for Python
Home-page: https://github.com/TargetProcess/signalr-client-py
Author: Taucraft Limited
Author-email: info@taucraft.com
License: Apache
Keywords: signalr
Platform: UNKNOWN
Classifier: Development Status :: 3 - Alpha
Classifier: Intended Audience :: Developers
Classifier: Topic :: Software Development :: Libraries :: Python Modules
Classifier: License :: OSI Approved :: Apache Software License
Classifier: Programming Language :: Python :: 2.7
Classifier: Programming Language :: Python :: 3
Classifier: Programming Language :: Python :: 3.2
Classifier: Programming Language :: Python :: 3.3
Classifier: Programming Language :: Python :: 3.4
Classifier: Programming Language :: Python :: 3.5
Requires-Dist: gevent
Requires-Dist: requests
Requires-Dist: sseclient
Requires-Dist: websocket-client
